{
  "camelcase": true,
  "indent": 2,
  "white": false,
  "curly": true,
  "eqeqeq": true,
  "immed": true,
  "latedef": true,
  "newcap": true,
  "noarg": true,
  "sub": true,
  "undef": true,
  "boss": true,
  "eqnull": true,
  "browser": true,
  "predef": {
    "alert": true,
    "confirm": true,
    "console": true,
    "test": true,
    "equal": true,
    "ok": true,
    "sinon": true,
    "require": true,
    "$": true,
    "jQuery": true,
    "Ember": true,
    "Handlebars": true,
    "App": true,
    "DS": true,
    "marked": true,
    "prettyPrintOne": true,
    "CodeMirror": true,
    "inlineAttach": true,
    "moment": true,
    "module": true,
    "test": true,
    "visit": true,
    "find": true,
    "andThen": true
  }
}

